setup.py
bin_probability/Binomialdistribution.py
bin_probability/Gaussiandistribution.py
bin_probability/Generaldistribution.py
bin_probability/__init__.py
bin_probability.egg-info/PKG-INFO
bin_probability.egg-info/SOURCES.txt
bin_probability.egg-info/dependency_links.txt
bin_probability.egg-info/not-zip-safe
bin_probability.egg-info/top_level.txt