Metadata-Version: 1.0
Name: bin-probability
Version: 0.1
Summary: Gaussian and Binomial distributions
Home-page: UNKNOWN
Author: Oscar Hernandez
Author-email: oehz_x@yahoo.es
License: UNKNOWN
Platform: UNKNOWN
